warpfield/__init__.py
warpfield/__main__.py
warpfield/ndimage.py
warpfield/register.py
warpfield/utils.py
warpfield/warp.py
warpfield/recipes/default.yml
warpfield/recipes/default_opm.yml
warpfield-0.2.2.dist-info/licenses/LICENSE
warpfield-0.2.2.dist-info/METADATA
warpfield-0.2.2.dist-info/WHEEL
warpfield-0.2.2.dist-info/entry_points.txt
warpfield-0.2.2.dist-info/top_level.txt
warpfield-0.2.2.dist-info/RECORD
