Metadata-Version: 2.4
Name: warpfield
Version: 0.2.2
Summary: GPU-accelerated 3D non-rigid registration
Author: jlab.berlin, Maximilian Hoffmann, Benjamin Judkewitz
License: MIT
Project-URL: Homepage, https://github.com/danionella/warpfield
Project-URL: Documentation, https://danionella.github.io/warpfield/
Keywords: warpfield,python
Classifier: Operating System :: Microsoft :: Windows
Classifier: Operating System :: POSIX :: Linux
Requires-Python: >=3.9
License-File: LICENSE
Requires-Dist: numpy
Requires-Dist: scipy
Requires-Dist: cupy-cuda12x
Requires-Dist: tqdm
Requires-Dist: pydantic
Requires-Dist: pyyaml
Requires-Dist: h5py
Requires-Dist: hdf5plugin
Requires-Dist: nibabel
Requires-Dist: tifffile
Requires-Dist: scikit-image
Requires-Dist: imageio
Requires-Dist: imageio-ffmpeg
Requires-Dist: pynrrd
Requires-Dist: zarr
Dynamic: license-file
